prefect_anyscale/__init__.py
prefect_anyscale/infrastructure.py
prefect_anyscale-0.2.2.dist-info/LICENSE
prefect_anyscale-0.2.2.dist-info/METADATA
prefect_anyscale-0.2.2.dist-info/WHEEL
prefect_anyscale-0.2.2.dist-info/top_level.txt
prefect_anyscale-0.2.2.dist-info/RECORD
